lockss/turtles/__init__.py
lockss/turtles/__main__.py
lockss/turtles/app.py
lockss/turtles/cli.py
lockss/turtles/plugin.py
lockss/turtles/plugin_registry.py
lockss/turtles/plugin_set.py
lockss/turtles/plugin_signing_credentials.py
lockss/turtles/util.py
unittest/lockss/turtles/__init__.py
unittest/lockss/turtles/test_plugin_registry.py
unittest/lockss/turtles/test_plugin_set.py
unittest/lockss/turtles/test_plugin_signing_credentials.py
lockss_turtles-0.6.0.dist-info/LICENSE
lockss_turtles-0.6.0.dist-info/METADATA
lockss_turtles-0.6.0.dist-info/WHEEL
lockss_turtles-0.6.0.dist-info/entry_points.txt
lockss_turtles-0.6.0.dist-info/RECORD
