Metadata-Version: 2.3
Name: lockss-turtles
Version: 0.6.0
Summary: Library and command line tool to manage LOCKSS plugin sets and LOCKSS plugin registries
License: BSD-3-Clause
Author: Thib Guicherd-Callin
Author-email: thib@cs.stanford.edu
Maintainer: Thib Guicherd-Callin
Maintainer-email: thib@cs.stanford.edu
Requires-Python: >=3.9,<4.0
Classifier: Development Status :: 5 - Production/Stable
Classifier: Environment :: Console
Classifier: Framework :: Pydantic :: 2
Classifier: Intended Audience :: Developers
Classifier: Intended Audience :: System Administrators
Classifier: License :: OSI Approved :: BSD License
Classifier: Programming Language :: Python
Classifier: Topic :: Software Development :: Libraries
Classifier: Topic :: System :: Archiving
Classifier: Topic :: Utilities
Requires-Dist: exceptiongroup (>=1.3.0,<1.4.0)
Requires-Dist: java-manifest (>=1.1.0,<1.2.0)
Requires-Dist: lockss-pybasic (>=0.1.1,<0.2.0)
Requires-Dist: pydantic (>=2.11.0,<2.12.0)
Requires-Dist: pyyaml (>=6.0.0,<6.1.0)
Requires-Dist: xdg (>=6.0.0,<6.1.0)
Project-URL: Documentation, https://docs.lockss.org/en/latest/software/turtles
Project-URL: Repository, https://github.com/lockss/lockss-turtles
Project-URL: changelog, https://github.com/lockss/lockss-turtles/blob/main/CHANGELOG.rst
Project-URL: issues, https://github.com/lockss/lockss-turtles/issues
